PyPetaKit5D/XR_FSC_analysis_wrapper.py
PyPetaKit5D/XR_MIP_wrapper.py
PyPetaKit5D/XR_bioformats_to_tiff_or_zarr_wrapper.py
PyPetaKit5D/XR_chromatic_shift_correction_data_wrapper.py
PyPetaKit5D/XR_crop_dataset.py
PyPetaKit5D/XR_decon_data_wrapper.py
PyPetaKit5D/XR_deskew_rotate_data_wrapper.py
PyPetaKit5D/XR_fftSpectrumComputingWrapper.py
PyPetaKit5D/XR_generate_image_list_wrapper.py
PyPetaKit5D/XR_imaris_conversion_data_wrapper.py
PyPetaKit5D/XR_matlab_stitching_wrapper.py
PyPetaKit5D/XR_microscopeAutomaticProcessing.py
PyPetaKit5D/XR_psf_analysis_wrapper.py
PyPetaKit5D/XR_psf_detection_and_analysis_wrapper.py
PyPetaKit5D/XR_resample_dataset.py
PyPetaKit5D/XR_resave_zarr_wrapper.py
PyPetaKit5D/XR_tiffToZarr_wrapper.py
PyPetaKit5D/XR_unmix_channels_data_wrapper.py
PyPetaKit5D/XR_visualize_OTF_mask_segmentation.py
PyPetaKit5D/XR_zarrToTiff_wrapper.py
PyPetaKit5D/__init__.py
PyPetaKit5D/generatePythonWrapper.py
PyPetaKit5D/generate_config_file.py
PyPetaKit5D/uninstall.py
pypetakit5d-1.4.6.dist-info/licenses/LICENSE.txt
pypetakit5d-1.4.6.dist-info/METADATA
pypetakit5d-1.4.6.dist-info/WHEEL
pypetakit5d-1.4.6.dist-info/entry_points.txt
pypetakit5d-1.4.6.dist-info/top_level.txt
pypetakit5d-1.4.6.dist-info/RECORD
