Metadata-Version: 2.4
Name: PyPetaKit5D
Version: 1.4.6
Summary: A Python wrapper for PetaKit5D
Home-page: https://github.com/abcucberkeley/PyPetaKit5D
Author: Matthew Mueller
Author-email: matthewmueller@berkeley.edu
License: GPL-3.0
Classifier: Intended Audience :: Science/Research
Classifier: Operating System :: POSIX :: Linux
Classifier: Programming Language :: Python :: 3.11
License-File: LICENSE.txt
Dynamic: author
Dynamic: author-email
Dynamic: classifier
Dynamic: home-page
Dynamic: license
Dynamic: license-file
Dynamic: summary
